flake8_testcode/__init__.py
flake8_testcode/flake8_missing_assertion.py
flake8_testcode-0.1.1.dist-info/entry_points.txt
flake8_testcode-0.1.1.dist-info/LICENSE
flake8_testcode-0.1.1.dist-info/WHEEL
flake8_testcode-0.1.1.dist-info/METADATA
flake8_testcode-0.1.1.dist-info/RECORD
