Metadata-Version: 2.1
Name: flake8-testcode
Version: 0.1.1
Summary: Plugin to catch bad style specific to testcode.
Home-page: https://github.com/Ewald91/flake8-testcode
License: MIT
Keywords: flake8,testcode,lint
Author: Ewald Verhoeven
Requires-Python: >=3.8,<4.0
Classifier: Framework :: Flake8
Classifier: License :: OSI Approved :: MIT License
Classifier: Programming Language :: Python :: 3
Classifier: Programming Language :: Python :: 3.8
Classifier: Programming Language :: Python :: 3.9
Classifier: Programming Language :: Python :: 3.10
Classifier: Programming Language :: Python :: 3.11
Classifier: Topic :: Software Development :: Libraries :: Python Modules
Classifier: Topic :: Software Development :: Quality Assurance
Requires-Dist: flake8 (>=3.8.4,<6)
Project-URL: Repository, https://github.com/Ewald91/flake8-testcode
